{
  "days": {
    "2026-02-18": [
      0.0,
      0.0,
      0.0,
      0.0,
      0.0,
      0.0,
      0.0,
      0.0,
      140.37,
      275.63,
      357.93,
      523.87,
      531.5,
      503.26,
      0.0,
      811.73,
      174.27,
      0.0,
      0.0,
      0.0,
      0.0,
      0.0,
      0.0,
      0.0
    ]
  },
  "last_snapshot": {
    "date": "2026-02-18",
    "hour": 16,
    "pv_kwh": 3572.2
  },
  "monthly_averages": {
    "2026-02": [
      0.0,
      0.0,
      0.0,
      0.0,
      0.0,
      0.0,
      0.0,
      0.0,
      0.0,
      0.0,
      0.0,
      0.0,
      0.0,
      0.0,
      0.0,
      0.0,
      0.0,
      0.0,
      0.0,
      0.0,
      0.0,
      0.0,
      0.0,
      0.0
    ]
  },
  "current_hour": 16
}